rawhdr/__init__.py
rawhdr/alignment.py
rawhdr/cli.py
rawhdr/common.py
rawhdr/exposure_fusion.py
rawhdr/focus_fusion.py
rawhdr/generic_fusion.py
rawhdr/test/__init__.py
rawhdr/test/test_common.py
rawhdr/test/test_exposure_fusion.py
rawhdr-0.11.3.dist-info/LICENSE
rawhdr-0.11.3.dist-info/METADATA
rawhdr-0.11.3.dist-info/WHEEL
rawhdr-0.11.3.dist-info/entry_points.txt
rawhdr-0.11.3.dist-info/top_level.txt
rawhdr-0.11.3.dist-info/RECORD
