Metadata-Version: 2.1
Name: rawhdr
Version: 0.11.3
Summary: A command-line image fuser for HDR exposure fusion, focus-stacking, etc.
Author-email: Felix Thaler <felix.thaler@nummi.ch>
License: GNU General Public License v2 or later (GPLv2+)
Project-URL: Homepage, https://github.com/fthaler/rawhdr
Project-URL: Bug Tracker, https://github.com/fthaler/rawhdr/issues
Classifier: Programming Language :: Python :: 3
Classifier: License :: OSI Approved :: GNU General Public License v2 or later (GPLv2+)
Classifier: Operating System :: OS Independent
Classifier: Topic :: Multimedia :: Graphics :: Graphics Conversion
Requires-Python: >=3.7
License-File: LICENSE
Requires-Dist: click
Requires-Dist: imageio
Requires-Dist: numpy
Requires-Dist: PyWavelets
Requires-Dist: rawpy
Requires-Dist: scipy
Requires-Dist: opencv-python
Requires-Dist: importlib-metadata ; python_version < "3.8"
